[{"id":"46576a95.003864","type":"tab","label":"Flow 1","disabled":false,"info":""},{"id":"5907b34b.b8753c","type":"rpi-gpio out","z":"46576a95.003864","name":"Green LED","pin":"11","set":"","level":"0","freq":"","out":"out","x":370,"y":380,"wires":[]},{"id":"79931c16.85cf64","type":"inject","z":"46576a95.003864","name":"On","topic":"","payload":"1","payloadType":"str","repeat":"","crontab":"","once":false,"onceDelay":0.1,"x":170,"y":340,"wires":[["5907b34b.b8753c"]]},{"id":"23c1f563.ee671a","type":"inject","z":"46576a95.003864","name":"Off","topic":"","payload":"0","payloadType":"str","repeat":"","crontab":"","once":false,"onceDelay":0.1,"x":170,"y":420,"wires":[["5907b34b.b8753c"]]}]